calculator5/__init__.py
calculator5/button_names.py
calculator5/calculator.py
calculator5/calculator_date.py
calculator5/calculator_date_page.py
calculator5/calculator_page.py
calculator5/calculator_standard_science.py
calculator5/programmer_page.py
calculator5/science_page.py
calculator5/standard_page.py
calculator5-2.1.0.dist-info/LICENSE
calculator5-2.1.0.dist-info/METADATA
calculator5-2.1.0.dist-info/WHEEL
calculator5-2.1.0.dist-info/top_level.txt
calculator5-2.1.0.dist-info/RECORD
